LICENSE
MANIFEST.in
README.rst
setup.py
django_pagination_plus.egg-info/PKG-INFO
django_pagination_plus.egg-info/SOURCES.txt
django_pagination_plus.egg-info/dependency_links.txt
django_pagination_plus.egg-info/top_level.txt
paginationplus/__init__.py
paginationplus/templatetags/__init__.py
paginationplus/templatetags/paginationplus.py