Metadata-Version: 1.0
Name: django-pagination-plus
Version: 0.0.3
Summary: Utilities for pagination in Django templates
Home-page: https://github.com/SteefH/django-pagination-plus
Author: Stefan van der Haven
Author-email: stefan@steeffie.net
License: UNKNOWN
Keywords: django,pagination
Platform: UNKNOWN
Classifier: Development Status :: 4 - Beta
Classifier: Framework :: Django
Classifier: Intended Audience :: Developers
Classifier: License :: OSI Approved :: BSD License
Classifier: Operating System :: OS Independent
Classifier: Programming Language :: Python
Classifier: Topic :: Internet :: WWW/HTTP
